{
  "version": 1,
  "base_track": "I Don’t Like Myself (Official Music Video)",
  "base_artist": "Imagine Dragons",
  "createdAt": "2026-02-06T17:51:59.745390Z",
  "candidates": [
    {
      "id": "lrclib_1",
      "source": "lrclib",
      "title": "I Don't Like Myself",
      "artist": "Imagine Dragons",
      "has_synced": true,
      "path": "select/01_I_Don't_Like_Myself_Imagine_Dragons.lrc"
    },
    {
      "id": "lrclib_2",
      "source": "lrclib",
      "title": "I Don’t Like Myself",
      "artist": "GIRLI",
      "has_synced": true,
      "path": "select/02_I_Don’t_Like_Myself_GIRLI.lrc"
    },
    {
      "id": "lrclib_3",
      "source": "lrclib",
      "title": "I Don't Like Myself",
      "artist": "Imagine Dragons",
      "has_synced": true,
      "path": "select/03_I_Don't_Like_Myself_Imagine_Dragons.lrc"
    },
    {
      "id": "lrclib_4",
      "source": "lrclib",
      "title": "I Don't Like Myself",
      "artist": "Imagine Dragons",
      "has_synced": true,
      "path": "select/04_I_Don't_Like_Myself_Imagine_Dragons.lrc"
    },
    {
      "id": "lrclib_5",
      "source": "lrclib",
      "title": "I Don't Like Myself",
      "artist": "Imagine Dragons",
      "has_synced": true,
      "path": "select/05_I_Don't_Like_Myself_Imagine_Dragons.lrc"
    },
    {
      "id": "lrclib_6",
      "source": "lrclib",
      "title": "I Don’t Like Myself",
      "artist": "Imagine Dragons",
      "has_synced": true,
      "path": "select/06_I_Don’t_Like_Myself_Imagine_Dragons.lrc"
    },
    {
      "id": "lrclib_7",
      "source": "lrclib",
      "title": "I Don't Like Myself",
      "artist": "Imagine Dragons",
      "has_synced": true,
      "path": "select/07_I_Don't_Like_Myself_Imagine_Dragons.lrc"
    },
    {
      "id": "lrclib_8",
      "source": "lrclib",
      "title": "I Don’t Like Myself",
      "artist": "Imagine Dragons",
      "has_synced": true,
      "path": "select/08_I_Don’t_Like_Myself_Imagine_Dragons.lrc"
    },
    {
      "id": "lrclib_9",
      "source": "lrclib",
      "title": "I Don’t Like Myself (Official Music Video)",
      "artist": "Imagine Dragons",
      "has_synced": true,
      "path": "select/09_I_Don’t_Like_Myself_(Official_Music_Video)_Imagine_Dragons.lrc"
    },
    {
      "id": "lrclib_10",
      "source": "lrclib",
      "title": "I Don’t Like Myself",
      "artist": "Imagine Dragons",
      "has_synced": true,
      "path": "select/10_I_Don’t_Like_Myself_Imagine_Dragons.lrc"
    },
    {
      "id": "lrclib_11",
      "source": "lrclib",
      "title": "I Don't Like Myself",
      "artist": "Clan of Xymox",
      "has_synced": false,
      "path": "select/11_I_Don't_Like_Myself_Clan_of_Xymox.txt"
    },
    {
      "id": "lrclib_12",
      "source": "lrclib",
      "title": "I Don't Like Myself (Paused)",
      "artist": "Imagine Dragons",
      "has_synced": true,
      "path": "select/12_I_Don't_Like_Myself_(Paused)_Imagine_Dragons.lrc"
    },
    {
      "id": "petitlyrics_1",
      "source": "petitlyrics",
      "title": "I Don't Like Myself",
      "artist": "Imagine Dragons",
      "has_synced": false,
      "path": "select/pl_01_I_Don't_Like_Myself_Imagine_Dragons.txt"
    }
  ]
}